wgm/__init__.py
wgm/__main__.py
wgm/__version__.py
wgm/command.py
wgm/commands/__init__.py
wgm/commands/create.py
wgm/commands/delete.py
wgm/commands/list.py
wgm/commands/version.py
wgm/config.py
wgm-0.1.6.dist-info/LICENSE
wgm-0.1.6.dist-info/METADATA
wgm-0.1.6.dist-info/WHEEL
wgm-0.1.6.dist-info/entry_points.txt
wgm-0.1.6.dist-info/RECORD
