Metadata-Version: 2.1
Name: wgm
Version: 0.1.6
Summary: WireGuard Manager (wgm) is a command-line tool designed to simplify the management of WireGuard VPN users. It allows you to easily create, list, and delete WireGuard users with a few simple commands.
Author: Roberto Lizana
Author-email: rober.lizana@gmail.com
Requires-Python: >=3.12,<4.0
Classifier: Programming Language :: Python :: 3
Classifier: Programming Language :: Python :: 3.12
Requires-Dist: cleo (>=2.1.0,<3.0.0)
